nodebpy/__init__.py
nodebpy/arrange.py
nodebpy/builder.py
nodebpy/nodes/__init__.py
nodebpy/nodes/attribute.py
nodebpy/nodes/curve.py
nodebpy/nodes/geometry.py
nodebpy/nodes/input.py
nodebpy/nodes/manually_specified.py
nodebpy/nodes/mesh.py
nodebpy/nodes/types.py
nodebpy/nodes/utilities.py
nodebpy/screenshot.py
nodebpy/screenshot_subprocess.py
nodebpy/sockets.py
nodebpy-0.1.0.dist-info/WHEEL
nodebpy-0.1.0.dist-info/entry_points.txt
nodebpy-0.1.0.dist-info/METADATA
nodebpy-0.1.0.dist-info/RECORD
