Metadata-Version: 2.3
Name: nodebpy
Version: 0.1.0
Summary: Build nodes in Blender with code
Author: Brady Johnston
Author-email: Brady Johnston <brady.johnston@me.com>
Requires-Dist: arrangebpy>=0.1.0
Requires-Dist: jsondiff>=2.2.1
Requires-Dist: syrupy>=5.0.0
Requires-Dist: tree-clipper>=0.1.1
Requires-Dist: bpy>=5.0.0 ; extra == 'bpy'
Requires-Dist: fake-bpy-module>=20260113 ; extra == 'dev'
Requires-Dist: pytest>=9.0.2 ; extra == 'dev'
Requires-Dist: pytest-cov>=7.0.0 ; extra == 'dev'
Requires-Dist: quarto-cli>=1.8.26 ; extra == 'dev'
Requires-Dist: quartodoc>=0.11.1 ; extra == 'dev'
Requires-Dist: ruff>=0.14.11 ; extra == 'dev'
Requires-Dist: ipython>=8.0.0 ; extra == 'jupyter'
Requires-Python: >=3.11
Provides-Extra: bpy
Provides-Extra: dev
Provides-Extra: jupyter
